feathersdk/__init__.py
feathersdk/comms/__init__.py
feathersdk/comms/comms_manager.py
feathersdk/comms/system.py
feathersdk/comms/socketcan_tcp/__init__.py
feathersdk/comms/socketcan_tcp/sct_error.h
feathersdk/comms/socketcan_tcp/sct_poll.h
feathersdk/comms/socketcan_tcp/sct_result.h
feathersdk/comms/socketcan_tcp/sct_sockets.h
feathersdk/comms/socketcan_tcp/sct_write.h
feathersdk/comms/socketcan_tcp/socketcan_tcp.c
feathersdk/robot/__init__.py
feathersdk/robot/battery_system.py
feathersdk/robot/instance_lock.py
feathersdk/robot/manipulation_platform.py
feathersdk/robot/navigation_platform.py
feathersdk/robot/neck_platform.py
feathersdk/robot/pinocchio_model.py
feathersdk/robot/robot.py
feathersdk/robot/robstride_neck_platform.py
feathersdk/robot/self_collision_checker.py
feathersdk/robot/steppable_system.py
feathersdk/robot/test_system.py
feathersdk/robot/torso_platform.py
feathersdk/robot/vision_platform.py
feathersdk/robot/motors/MMS760200-48-C2-1.eds
feathersdk/robot/motors/MMS760400-48-C2-1.eds
feathersdk/robot/motors/__init__.py
feathersdk/robot/motors/feetech_simple.py
feathersdk/robot/motors/motors_manager.py
feathersdk/robot/motors/myactuator.py
feathersdk/utils/__init__.py
feathersdk/utils/constants.py
feathersdk/utils/files.py
feathersdk/utils/format.py
feathersdk/utils/hydra_helper.py
feathersdk/utils/logger.py
feathersdk/utils/perf_logger.py
feathersdk/utils/timeout.py
feathersdk/utils/trajectory.py
feathersdk/utils/urdf_convex_hull.py
feathersdk-0.0.7.dist-info/METADATA
feathersdk-0.0.7.dist-info/WHEEL
feathersdk-0.0.7.dist-info/top_level.txt
feathersdk-0.0.7.dist-info/RECORD
