Metadata-Version: 2.4
Name: feathersdk
Version: 0.0.7
Summary: Feather Python SDK Library
Author: Feather Robotics Inc.
License: "MIT"
Platform: unix
Platform: linux
Platform: osx
Classifier: Programming Language :: Python :: 3
Classifier: Programming Language :: Python :: 3 :: Only
Classifier: Programming Language :: Python :: 3.9
Classifier: Programming Language :: Python :: 3.10
Classifier: Programming Language :: Python :: 3.11
Classifier: Programming Language :: Python :: 3.12
Requires-Python: >=3.9
Requires-Dist: canopen
Requires-Dist: typing_extensions
Requires-Dist: filelock
Requires-Dist: numpy
Requires-Dist: psutil
Requires-Dist: smbus2
Requires-Dist: hydra-core
Dynamic: description
Dynamic: description-content-type
Dynamic: requires-dist
